bascom/__init__.py
bascom/py.typed
bascom/utils.py
bascom-0.1.2.dist-info/METADATA
bascom-0.1.2.dist-info/WHEEL
bascom-0.1.2.dist-info/licenses/LICENSE.txt
bascom-0.1.2.dist-info/RECORD
