Metadata-Version: 2.4
Name: bascom
Version: 0.1.2
Summary: Core library that my tools use.
License-Expression: MIT
License-File: LICENSE.txt
Keywords: library,logging,utilities
Author: Andrew Udvare
Author-email: audvare@gmail.com
Requires-Python: >=3.10,<4.0
Classifier: Development Status :: 4 - Beta
Classifier: Intended Audience :: Developers
Classifier: Programming Language :: Python
Classifier: Programming Language :: Python :: 3.10
Classifier: Programming Language :: Python :: 3.11
Classifier: Programming Language :: Python :: 3.12
Classifier: Programming Language :: Python :: 3.13
Classifier: Programming Language :: Python :: 3.14
Classifier: Typing :: Typed
Requires-Dist: colorlog (>=6.10.1,<7.0.0)
Requires-Dist: typing-extensions (>=4.15.0,<5.0.0)
Project-URL: Documentation, https://bascom.readthedocs.org
Project-URL: Homepage, https://tatsh.github.io/bascom/
Project-URL: Issues, https://github.com/Tatsh/bascom/issues
Project-URL: Repository, https://github.com/Tatsh/bascom
